deepmerit/__init__.py
deepmerit/adverseEvents/__init__.py
deepmerit/adverseEvents/ade.py
deepmerit/adverseEvents/classify_events.py
deepmerit/adverseEvents/extract_data.py
deepmerit/adverseEvents/prescribe.py
deepmerit/bioLemmatizer/__init__.py
deepmerit/bioLemmatizer/bio_lemm.py
deepmerit/bioLemmatizer/classifier.py
deepmerit/bioLemmatizer/read_notes.py
deepmerit/bioLemmatizer/suggestion.py
deepmerit/counterfeitDrugs/__init__.py
deepmerit/counterfeitDrugs/adanet_classifier.py
deepmerit/counterfeitDrugs/counterfeit.py
deepmerit/counterfeitDrugs/cpca_image.py
deepmerit/counterfeitDrugs/dshap.py
deepmerit/counterfeitDrugs/multi_accuracy.py
deepmerit/counterfeitDrugs/read_image.py
deepmerit/multiAccuracy/__init__.py
deepmerit/multiAccuracy/architecture.py
deepmerit/multiAccuracy/classifier.py
deepmerit/wrapper/__init__.py
deepmerit/wrapper/boto3.py
deepmerit-2.1.dist-info/LICENSE
deepmerit-2.1.dist-info/METADATA
deepmerit-2.1.dist-info/WHEEL
deepmerit-2.1.dist-info/top_level.txt
deepmerit-2.1.dist-info/RECORD
