Metadata-Version: 2.1
Name: deepmerit
Version: 2.1
Summary: DeepMerit package
Home-page: https://github.com/Virtusa-vLife/deepmerit
Author: Virtusa
Author-email: namagupta@virtusa.com
License: UNKNOWN
Platform: UNKNOWN
Classifier: Programming Language :: Python :: 3
Classifier: License :: OSI Approved :: MIT License
Classifier: Operating System :: OS Independent
